<?xml version="1.0" encoding="UTF-8"?>
<con:soapui-project id="1db8cdf0-3ae1-4cbf-b531-65ff0d3d4191" activeEnvironment="Default" name="SpringBootRestServiceDemo" resourceRoot="" soapui-version="5.2.1" abortOnError="false" runType="SEQUENTIAL" xmlns:con="http://eviware.com/soapui/config"><con:settings/><con:interface xsi:type="con:RestService" id="408dea9b-be5a-4d1d-9372-685edede5592" wadlVersion="http://wadl.dev.java.net/2009/02" name="http://localhost:6070" type="rest" xmlns:xsi="http://www.w3.org/2001/XMLSchema-instance"><con:settings/><con:definitionCache/><con:endpoints><con:endpoint>http://localhost:6070</con:endpoint></con:endpoints><con:resource name="v1" path="/multipleCustomer/v1/welcome" id="958f88a6-e34b-4887-adbd-f3c40da39eef"><con:settings/><con:parameters/><con:method name="greetingTime" id="d3d3c6b8-d801-4a53-a9fb-dda07033dd50" method="GET"><con:settings/><con:parameters/><con:representation type="RESPONSE"><con:mediaType>application/json;charset=UTF-8</con:mediaType><con:status>200</con:status><con:params/></con:representation><con:request name="Request 1" id="365ad868-d192-4738-aa8a-0a8403c3915f" mediaType="application/json"><con:settings><con:setting id="com.eviware.soapui.impl.wsdl.WsdlRequest@request-headers">&lt;xml-fragment/></con:setting></con:settings><con:endpoint>http://localhost:6070</con:endpoint><con:request/><con:originalUri>http://localhost/multipleCustomer/v1/manu</con:originalUri><con:credentials><con:authType>No Authorization</con:authType></con:credentials><con:jmsConfig JMSDeliveryMode="PERSISTENT"/><con:jmsPropertyConfig/><con:parameters/></con:request></con:method></con:resource><con:resource name="v2" path="/multipleCustomer/v1/empConfig" id="958f88a6-e34b-4887-adbd-f3c40da39eef"><con:settings/><con:parameters/><con:method name="getEmpConfiguration" id="d3d3c6b8-d801-4a53-a9fb-dda07033dd50" method="POST"><con:settings/><con:parameters/><con:representation type="RESPONSE"><con:mediaType>application/json;charset=UTF-8</con:mediaType><con:status>200</con:status><con:params/></con:representation><con:representation type="REQUEST"><con:mediaType>application/json</con:mediaType><con:params/></con:representation><con:request name="Request 1" id="365ad868-d192-4738-aa8a-0a8403c3915f" mediaType="application/json" postQueryString="false"><con:settings><con:setting id="com.eviware.soapui.impl.wsdl.WsdlRequest@request-headers">&lt;xml-fragment/></con:setting></con:settings><con:endpoint>http://localhost:6070</con:endpoint><con:request>{
"id" : 1
}</con:request><con:originalUri>http://localhost/multipleCustomer/v1/manu</con:originalUri><con:credentials><con:authType>No Authorization</con:authType></con:credentials><con:jmsConfig JMSDeliveryMode="PERSISTENT"/><con:jmsPropertyConfig/><con:parameters/></con:request></con:method></con:resource><con:resource name="v3" path="/multipleCustomer/v1/custDetails" id="958f88a6-e34b-4887-adbd-f3c40da39eef"><con:settings/><con:parameters/><con:method name="getCustConfiguration" id="d3d3c6b8-d801-4a53-a9fb-dda07033dd50" method="POST"><con:settings/><con:parameters/><con:representation type="RESPONSE"><con:mediaType>application/json;charset=UTF-8</con:mediaType><con:status>200</con:status><con:params/></con:representation><con:representation type="REQUEST"><con:mediaType>application/json</con:mediaType><con:params/></con:representation><con:representation type="RESPONSE"><con:mediaType xsi:nil="true"/><con:status>200</con:status><con:params/><con:element>data</con:element></con:representation><con:request name="Request 1" id="365ad868-d192-4738-aa8a-0a8403c3915f" mediaType="application/json" postQueryString="false"><con:settings><con:setting id="com.eviware.soapui.impl.wsdl.WsdlRequest@request-headers">&lt;xml-fragment/></con:setting></con:settings><con:endpoint>http://localhost:6070</con:endpoint><con:request>{
"id" : 4
}</con:request><con:originalUri>http://localhost/multipleCustomer/v1/manu</con:originalUri><con:credentials><con:authType>No Authorization</con:authType></con:credentials><con:jmsConfig JMSDeliveryMode="PERSISTENT"/><con:jmsPropertyConfig/><con:parameters/></con:request></con:method></con:resource><con:resource name="v4" path="/multipleCustomer/v1/myCustomer" id="958f88a6-e34b-4887-adbd-f3c40da39eef"><con:settings/><con:parameters/><con:method name="getNameCustomer" id="d3d3c6b8-d801-4a53-a9fb-dda07033dd50" method="POST"><con:settings/><con:parameters/><con:representation type="RESPONSE"><con:mediaType>application/json;charset=UTF-8</con:mediaType><con:status>200</con:status><con:params/></con:representation><con:representation type="REQUEST"><con:mediaType>application/json</con:mediaType><con:params/></con:representation><con:representation type="FAULT"><con:mediaType>application/json;charset=UTF-8</con:mediaType><con:status>500</con:status><con:params/><con:element xmlns:manu="http://localhost/multipleCustomer/v1/manu">manu:Fault</con:element></con:representation><con:representation type="RESPONSE"><con:mediaType xsi:nil="true"/><con:status>0</con:status><con:params/><con:element>data</con:element></con:representation><con:request name="Request 1" id="365ad868-d192-4738-aa8a-0a8403c3915f" mediaType="application/json" postQueryString="false"><con:settings><con:setting id="com.eviware.soapui.impl.wsdl.WsdlRequest@request-headers">&lt;xml-fragment/></con:setting></con:settings><con:endpoint>http://localhost:6070</con:endpoint><con:request>{
"id" : 5
}</con:request><con:originalUri>http://localhost/multipleCustomer/v1/manu</con:originalUri><con:credentials><con:authType>No Authorization</con:authType></con:credentials><con:jmsConfig JMSDeliveryMode="PERSISTENT"/><con:jmsPropertyConfig/><con:parameters/></con:request></con:method></con:resource><con:resource name="v5" path="/multipleCustomer/v1/qeRow" id="958f88a6-e34b-4887-adbd-f3c40da39eef"><con:settings/><con:parameters/><con:method name="queryRow" id="d3d3c6b8-d801-4a53-a9fb-dda07033dd50" method="GET"><con:settings/><con:parameters/><con:representation type="RESPONSE"><con:mediaType>application/json;charset=UTF-8</con:mediaType><con:status>200</con:status><con:params/></con:representation><con:representation type="REQUEST"><con:mediaType>application/json</con:mediaType><con:params/></con:representation><con:representation type="FAULT"><con:mediaType>application/json;charset=UTF-8</con:mediaType><con:status>500 415</con:status><con:params/><con:element xmlns:manu="http://localhost/multipleCustomer/v1/manu">manu:Fault</con:element></con:representation><con:representation type="RESPONSE"><con:mediaType xsi:nil="true"/><con:status>0</con:status><con:params/><con:element>data</con:element></con:representation><con:request name="Request 1" id="365ad868-d192-4738-aa8a-0a8403c3915f" mediaType="application/json" postQueryString="false"><con:settings><con:setting id="com.eviware.soapui.impl.wsdl.WsdlRequest@request-headers">&lt;xml-fragment/></con:setting></con:settings><con:endpoint>http://localhost:6070</con:endpoint><con:request/><con:originalUri>http://localhost/multipleCustomer/v1/manu</con:originalUri><con:credentials><con:authType>No Authorization</con:authType></con:credentials><con:jmsConfig JMSDeliveryMode="PERSISTENT"/><con:jmsPropertyConfig/><con:parameters/></con:request></con:method></con:resource><con:resource name="v6" path="/multipleCustomer/v1/userExist" id="958f88a6-e34b-4887-adbd-f3c40da39eef"><con:settings/><con:parameters/><con:method name="isUserExist" id="d3d3c6b8-d801-4a53-a9fb-dda07033dd50" method="POST"><con:settings/><con:parameters/><con:representation type="RESPONSE"><con:mediaType>application/json;charset=UTF-8</con:mediaType><con:status>200</con:status><con:params/></con:representation><con:representation type="REQUEST"><con:mediaType>application/json</con:mediaType><con:params/></con:representation><con:representation type="FAULT"><con:mediaType>application/json;charset=UTF-8</con:mediaType><con:status>500</con:status><con:params/><con:element xmlns:manu="http://localhost/multipleCustomer/v1/manu">manu:Fault</con:element></con:representation><con:representation type="RESPONSE"><con:mediaType xsi:nil="true"/><con:status>0</con:status><con:params/><con:element>data</con:element></con:representation><con:request name="Request 1" id="365ad868-d192-4738-aa8a-0a8403c3915f" mediaType="application/json" postQueryString="false"><con:settings><con:setting id="com.eviware.soapui.impl.wsdl.WsdlRequest@request-headers">&lt;xml-fragment/></con:setting></con:settings><con:endpoint>http://localhost:6070</con:endpoint><con:request>{
"firstName" : "Shraddha"
}</con:request><con:originalUri>http://localhost/multipleCustomer/v1/manu</con:originalUri><con:credentials><con:authType>No Authorization</con:authType></con:credentials><con:jmsConfig JMSDeliveryMode="PERSISTENT"/><con:jmsPropertyConfig/><con:parameters/></con:request></con:method></con:resource><con:resource name="v7" path="/multipleCustomer/v1/custAddress" id="958f88a6-e34b-4887-adbd-f3c40da39eef"><con:settings/><con:parameters/><con:method name="getCustAddress" id="d3d3c6b8-d801-4a53-a9fb-dda07033dd50" method="POST"><con:settings/><con:parameters/><con:representation type="RESPONSE"><con:mediaType>application/json;charset=UTF-8</con:mediaType><con:status>200</con:status><con:params/></con:representation><con:representation type="REQUEST"><con:mediaType>application/json</con:mediaType><con:params/></con:representation><con:representation type="FAULT"><con:mediaType>application/json;charset=UTF-8</con:mediaType><con:status>500</con:status><con:params/><con:element xmlns:manu="http://localhost/multipleCustomer/v1/manu">manu:Fault</con:element></con:representation><con:representation type="RESPONSE"><con:mediaType xsi:nil="true"/><con:status>0</con:status><con:params/><con:element>data</con:element></con:representation><con:representation type="RESPONSE"><con:mediaType xsi:nil="true"/><con:status>0</con:status><con:params/><con:element>data</con:element></con:representation><con:representation type="RESPONSE"><con:mediaType xsi:nil="true"/><con:status>200</con:status><con:params/><con:element>data</con:element></con:representation><con:representation type="RESPONSE"><con:mediaType xsi:nil="true"/><con:status>200</con:status><con:params/><con:element>data</con:element></con:representation><con:representation type="RESPONSE"><con:mediaType xsi:nil="true"/><con:status>200</con:status><con:params/><con:element>data</con:element></con:representation><con:request name="Request 1" id="365ad868-d192-4738-aa8a-0a8403c3915f" mediaType="application/json" postQueryString="false"><con:settings><con:setting id="com.eviware.soapui.impl.wsdl.WsdlRequest@request-headers">&lt;xml-fragment/></con:setting></con:settings><con:endpoint>http://localhost:6070</con:endpoint><con:request>{
"custName" : "Shraddha"
}</con:request><con:originalUri>http://localhost/multipleCustomer/v1/manu</con:originalUri><con:credentials><con:authType>No Authorization</con:authType></con:credentials><con:jmsConfig JMSDeliveryMode="PERSISTENT"/><con:jmsPropertyConfig/><con:parameters/></con:request></con:method></con:resource><con:resource name="v8" path="/multipleCustomer/v1/custAddressCommon" id="958f88a6-e34b-4887-adbd-f3c40da39eef"><con:settings/><con:parameters/><con:method name="getCustAddressCommon" id="d3d3c6b8-d801-4a53-a9fb-dda07033dd50" method="POST"><con:settings/><con:parameters/><con:representation type="RESPONSE"><con:mediaType>application/json;charset=UTF-8</con:mediaType><con:status>200</con:status><con:params/></con:representation><con:representation type="REQUEST"><con:mediaType>application/json</con:mediaType><con:params/></con:representation><con:representation type="FAULT"><con:mediaType>application/json;charset=UTF-8</con:mediaType><con:status>500</con:status><con:params/><con:element xmlns:manu="http://localhost/multipleCustomer/v1/manu">manu:Fault</con:element></con:representation><con:representation type="RESPONSE"><con:mediaType xsi:nil="true"/><con:status>0</con:status><con:params/><con:element>data</con:element></con:representation><con:representation type="RESPONSE"><con:mediaType xsi:nil="true"/><con:status>0</con:status><con:params/><con:element>data</con:element></con:representation><con:representation type="RESPONSE"><con:mediaType xsi:nil="true"/><con:status>200</con:status><con:params/><con:element>data</con:element></con:representation><con:representation type="RESPONSE"><con:mediaType xsi:nil="true"/><con:status>200</con:status><con:params/><con:element>data</con:element></con:representation><con:representation type="RESPONSE"><con:mediaType xsi:nil="true"/><con:status>0</con:status><con:params/><con:element>data</con:element></con:representation><con:request name="Request 1" id="365ad868-d192-4738-aa8a-0a8403c3915f" mediaType="application/json" postQueryString="false"><con:settings><con:setting id="com.eviware.soapui.impl.wsdl.WsdlRequest@request-headers">&lt;xml-fragment/></con:setting></con:settings><con:endpoint>http://localhost:6070</con:endpoint><con:request>{
"location" : "Sec49"
}</con:request><con:originalUri>http://localhost/multipleCustomer/v1/manu</con:originalUri><con:credentials><con:authType>No Authorization</con:authType></con:credentials><con:jmsConfig JMSDeliveryMode="PERSISTENT"/><con:jmsPropertyConfig/><con:parameters/></con:request></con:method></con:resource><con:resource name="v9" path="/multipleCustomer/v1/custEmail" id="958f88a6-e34b-4887-adbd-f3c40da39eef"><con:settings/><con:parameters/><con:method name="getCustEmail" id="d3d3c6b8-d801-4a53-a9fb-dda07033dd50" method="POST"><con:settings/><con:parameters/><con:representation type="RESPONSE"><con:mediaType>application/json;charset=UTF-8</con:mediaType><con:status>200</con:status><con:params/></con:representation><con:representation type="REQUEST"><con:mediaType>application/json</con:mediaType><con:params/></con:representation><con:representation type="FAULT"><con:mediaType>application/json;charset=UTF-8</con:mediaType><con:status>500</con:status><con:params/><con:element xmlns:manu="http://localhost/multipleCustomer/v1/manu">manu:Fault</con:element></con:representation><con:representation type="RESPONSE"><con:mediaType xsi:nil="true"/><con:status>0</con:status><con:params/><con:element>data</con:element></con:representation><con:representation type="RESPONSE"><con:mediaType xsi:nil="true"/><con:status>0</con:status><con:params/><con:element>data</con:element></con:representation><con:representation type="RESPONSE"><con:mediaType xsi:nil="true"/><con:status>200</con:status><con:params/><con:element>data</con:element></con:representation><con:representation type="RESPONSE"><con:mediaType xsi:nil="true"/><con:status>200</con:status><con:params/><con:element>data</con:element></con:representation><con:representation type="RESPONSE"><con:mediaType xsi:nil="true"/><con:status>0</con:status><con:params/><con:element>data</con:element></con:representation><con:request name="Request 1" id="365ad868-d192-4738-aa8a-0a8403c3915f" mediaType="application/json" postQueryString="false"><con:settings><con:setting id="com.eviware.soapui.impl.wsdl.WsdlRequest@request-headers">&lt;xml-fragment/></con:setting></con:settings><con:endpoint>http://localhost:6070</con:endpoint><con:request>{
"firstName" : "Roli"
}</con:request><con:originalUri>http://localhost/multipleCustomer/v1/manu</con:originalUri><con:credentials><con:authType>No Authorization</con:authType></con:credentials><con:jmsConfig JMSDeliveryMode="PERSISTENT"/><con:jmsPropertyConfig/><con:parameters/></con:request></con:method></con:resource><con:resource name="v10" path="/multipleCustomer/v1/itemConfig" id="958f88a6-e34b-4887-adbd-f3c40da39eef"><con:settings/><con:parameters/><con:method name="getItemConfiguration" id="d3d3c6b8-d801-4a53-a9fb-dda07033dd50" method="POST"><con:settings/><con:parameters/><con:representation type="RESPONSE"><con:mediaType>application/json;charset=UTF-8</con:mediaType><con:status>200</con:status><con:params/></con:representation><con:representation type="REQUEST"><con:mediaType>application/json</con:mediaType><con:params/></con:representation><con:representation type="FAULT"><con:mediaType>application/json;charset=UTF-8</con:mediaType><con:status>500</con:status><con:params/><con:element xmlns:manu="http://localhost/multipleCustomer/v1/manu">manu:Fault</con:element></con:representation><con:representation type="RESPONSE"><con:mediaType xsi:nil="true"/><con:status>0</con:status><con:params/><con:element>data</con:element></con:representation><con:representation type="RESPONSE"><con:mediaType xsi:nil="true"/><con:status>0</con:status><con:params/><con:element>data</con:element></con:representation><con:representation type="RESPONSE"><con:mediaType xsi:nil="true"/><con:status>200</con:status><con:params/><con:element>data</con:element></con:representation><con:representation type="RESPONSE"><con:mediaType xsi:nil="true"/><con:status>200</con:status><con:params/><con:element>data</con:element></con:representation><con:representation type="RESPONSE"><con:mediaType xsi:nil="true"/><con:status>0</con:status><con:params/><con:element>data</con:element></con:representation><con:request name="Request 1" id="365ad868-d192-4738-aa8a-0a8403c3915f" mediaType="application/json" postQueryString="false"><con:settings><con:setting id="com.eviware.soapui.impl.wsdl.WsdlRequest@request-headers">&lt;xml-fragment/></con:setting></con:settings><con:endpoint>http://localhost:6070</con:endpoint><con:request>{
"itemId" : "STE="
}</con:request><con:originalUri>http://localhost/multipleCustomer/v1/manu</con:originalUri><con:credentials><con:authType>No Authorization</con:authType></con:credentials><con:jmsConfig JMSDeliveryMode="PERSISTENT"/><con:jmsPropertyConfig/><con:parameters/></con:request></con:method></con:resource><con:resource name="v11" path="/multipleCustomer/v1/marketConfig" id="958f88a6-e34b-4887-adbd-f3c40da39eef"><con:settings/><con:parameters/><con:method name="getMarketConfiguration" id="d3d3c6b8-d801-4a53-a9fb-dda07033dd50" method="POST"><con:settings/><con:parameters/><con:representation type="RESPONSE"><con:mediaType>application/json;charset=UTF-8</con:mediaType><con:status>200</con:status><con:params/></con:representation><con:representation type="REQUEST"><con:mediaType>application/json</con:mediaType><con:params/></con:representation><con:representation type="FAULT"><con:mediaType>application/json;charset=UTF-8</con:mediaType><con:status>500 400</con:status><con:params/><con:element xmlns:manu="http://localhost/multipleCustomer/v1/manu">manu:Fault</con:element></con:representation><con:representation type="RESPONSE"><con:mediaType xsi:nil="true"/><con:status>0</con:status><con:params/><con:element>data</con:element></con:representation><con:representation type="RESPONSE"><con:mediaType xsi:nil="true"/><con:status>0</con:status><con:params/><con:element>data</con:element></con:representation><con:representation type="RESPONSE"><con:mediaType xsi:nil="true"/><con:status>200</con:status><con:params/><con:element>data</con:element></con:representation><con:representation type="RESPONSE"><con:mediaType xsi:nil="true"/><con:status>200</con:status><con:params/><con:element>data</con:element></con:representation><con:representation type="RESPONSE"><con:mediaType xsi:nil="true"/><con:status>0</con:status><con:params/><con:element>data</con:element></con:representation><con:representation type="RESPONSE"><con:mediaType xsi:nil="true"/><con:status>0</con:status><con:params/><con:element>data</con:element></con:representation><con:representation type="RESPONSE"><con:mediaType xsi:nil="true"/><con:status>0</con:status><con:params/><con:element>data</con:element></con:representation><con:request name="Request 1" id="365ad868-d192-4738-aa8a-0a8403c3915f" mediaType="application/json" postQueryString="false"><con:settings><con:setting id="com.eviware.soapui.impl.wsdl.WsdlRequest@request-headers">&lt;xml-fragment/></con:setting></con:settings><con:endpoint>http://localhost:6070</con:endpoint><con:request>{
"marketId" : 1423
}</con:request><con:originalUri>http://localhost/multipleCustomer/v1/manu</con:originalUri><con:credentials><con:authType>No Authorization</con:authType></con:credentials><con:jmsConfig JMSDeliveryMode="PERSISTENT"/><con:jmsPropertyConfig/><con:parameters/></con:request></con:method></con:resource><con:resource name="v12" path="/multipleCustomer/v1/marketEffective" id="958f88a6-e34b-4887-adbd-f3c40da39eef"><con:settings/><con:parameters/><con:method name="getMarketByEffectiveDate" id="d3d3c6b8-d801-4a53-a9fb-dda07033dd50" method="POST"><con:settings/><con:parameters/><con:representation type="RESPONSE"><con:mediaType>application/json;charset=UTF-8</con:mediaType><con:status>200</con:status><con:params/></con:representation><con:representation type="REQUEST"><con:mediaType>application/json</con:mediaType><con:params/></con:representation><con:representation type="FAULT"><con:mediaType>application/json;charset=UTF-8</con:mediaType><con:status>500 400</con:status><con:params/><con:element xmlns:manu="http://localhost/multipleCustomer/v1/manu">manu:Fault</con:element></con:representation><con:representation type="RESPONSE"><con:mediaType xsi:nil="true"/><con:status>0</con:status><con:params/><con:element>data</con:element></con:representation><con:representation type="RESPONSE"><con:mediaType xsi:nil="true"/><con:status>0</con:status><con:params/><con:element>data</con:element></con:representation><con:representation type="RESPONSE"><con:mediaType xsi:nil="true"/><con:status>200</con:status><con:params/><con:element>data</con:element></con:representation><con:representation type="RESPONSE"><con:mediaType xsi:nil="true"/><con:status>200</con:status><con:params/><con:element>data</con:element></con:representation><con:representation type="RESPONSE"><con:mediaType xsi:nil="true"/><con:status>0</con:status><con:params/><con:element>data</con:element></con:representation><con:representation type="RESPONSE"><con:mediaType xsi:nil="true"/><con:status>0</con:status><con:params/><con:element>data</con:element></con:representation><con:representation type="RESPONSE"><con:mediaType xsi:nil="true"/><con:status>0</con:status><con:params/><con:element>data</con:element></con:representation><con:representation type="RESPONSE"><con:mediaType xsi:nil="true"/><con:status>200</con:status><con:params/><con:element>data</con:element></con:representation><con:representation type="RESPONSE"><con:mediaType xsi:nil="true"/><con:status>200</con:status><con:params/><con:element>data</con:element></con:representation><con:representation type="RESPONSE"><con:mediaType xsi:nil="true"/><con:status>0</con:status><con:params/><con:element>data</con:element></con:representation><con:request name="Request 1" id="365ad868-d192-4738-aa8a-0a8403c3915f" mediaType="application/json" postQueryString="false"><con:settings><con:setting id="com.eviware.soapui.impl.wsdl.WsdlRequest@request-headers">&lt;xml-fragment/></con:setting></con:settings><con:endpoint>http://localhost:6070</con:endpoint><con:request>{
"effectiveDate" : "2011-01-24"
}</con:request><con:originalUri>http://localhost/multipleCustomer/v1/manu</con:originalUri><con:credentials><con:authType>No Authorization</con:authType></con:credentials><con:jmsConfig JMSDeliveryMode="PERSISTENT"/><con:jmsPropertyConfig/><con:parameters/></con:request></con:method></con:resource><con:resource name="v13" path="/multipleCustomer/v1/vendorConfig" id="958f88a6-e34b-4887-adbd-f3c40da39eef"><con:settings/><con:parameters/><con:method name="getVendorConfiguration" id="d3d3c6b8-d801-4a53-a9fb-dda07033dd50" method="POST"><con:settings/><con:parameters/><con:representation type="RESPONSE"><con:mediaType>application/json;charset=UTF-8</con:mediaType><con:status>200</con:status><con:params/></con:representation><con:representation type="REQUEST"><con:mediaType>application/json</con:mediaType><con:params/></con:representation><con:representation type="FAULT"><con:mediaType>application/json;charset=UTF-8</con:mediaType><con:status>500 400</con:status><con:params/><con:element xmlns:manu="http://localhost/multipleCustomer/v1/manu">manu:Fault</con:element></con:representation><con:representation type="RESPONSE"><con:mediaType xsi:nil="true"/><con:status>0</con:status><con:params/><con:element>data</con:element></con:representation><con:representation type="RESPONSE"><con:mediaType xsi:nil="true"/><con:status>0</con:status><con:params/><con:element>data</con:element></con:representation><con:representation type="RESPONSE"><con:mediaType xsi:nil="true"/><con:status>200</con:status><con:params/><con:element>data</con:element></con:representation><con:representation type="RESPONSE"><con:mediaType xsi:nil="true"/><con:status>200</con:status><con:params/><con:element>data</con:element></con:representation><con:representation type="RESPONSE"><con:mediaType xsi:nil="true"/><con:status>0</con:status><con:params/><con:element>data</con:element></con:representation><con:representation type="RESPONSE"><con:mediaType xsi:nil="true"/><con:status>0</con:status><con:params/><con:element>data</con:element></con:representation><con:representation type="RESPONSE"><con:mediaType xsi:nil="true"/><con:status>0</con:status><con:params/><con:element>data</con:element></con:representation><con:representation type="RESPONSE"><con:mediaType xsi:nil="true"/><con:status>200</con:status><con:params/><con:element>data</con:element></con:representation><con:representation type="RESPONSE"><con:mediaType xsi:nil="true"/><con:status>200</con:status><con:params/><con:element>data</con:element></con:representation><con:representation type="RESPONSE"><con:mediaType xsi:nil="true"/><con:status>0</con:status><con:params/><con:element>data</con:element></con:representation><con:representation type="RESPONSE"><con:mediaType xsi:nil="true"/><con:status>0</con:status><con:params/><con:element>data</con:element></con:representation><con:representation type="RESPONSE"><con:mediaType xsi:nil="true"/><con:status>0</con:status><con:params/><con:element>data</con:element></con:representation><con:request name="Request 1" id="365ad868-d192-4738-aa8a-0a8403c3915f" mediaType="application/json" postQueryString="false"><con:settings><con:setting id="com.eviware.soapui.impl.wsdl.WsdlRequest@request-headers">&lt;xml-fragment/></con:setting></con:settings><con:endpoint>http://localhost:6070</con:endpoint><con:request>{
"vendorID" : "V1"
}</con:request><con:originalUri>http://localhost/multipleCustomer/v1/manu</con:originalUri><con:credentials><con:authType>No Authorization</con:authType></con:credentials><con:jmsConfig JMSDeliveryMode="PERSISTENT"/><con:jmsPropertyConfig/><con:parameters/></con:request></con:method></con:resource><con:resource name="v14" path="/multipleCustomer/v1/custDetailsHibernate" id="958f88a6-e34b-4887-adbd-f3c40da39eef"><con:settings/><con:parameters/><con:method name="getCustHibnerte" id="d3d3c6b8-d801-4a53-a9fb-dda07033dd50" method="POST"><con:settings/><con:parameters/><con:representation type="RESPONSE"><con:mediaType>application/json;charset=UTF-8</con:mediaType><con:status>200</con:status><con:params/></con:representation><con:representation type="REQUEST"><con:mediaType>application/json</con:mediaType><con:params/></con:representation><con:representation type="FAULT"><con:mediaType>application/json;charset=UTF-8</con:mediaType><con:status>500 400</con:status><con:params/><con:element xmlns:manu="http://localhost/multipleCustomer/v1/manu">manu:Fault</con:element></con:representation><con:representation type="RESPONSE"><con:mediaType xsi:nil="true"/><con:status>0</con:status><con:params/><con:element>data</con:element></con:representation><con:representation type="RESPONSE"><con:mediaType xsi:nil="true"/><con:status>0</con:status><con:params/><con:element>data</con:element></con:representation><con:representation type="RESPONSE"><con:mediaType xsi:nil="true"/><con:status>200</con:status><con:params/><con:element>data</con:element></con:representation><con:representation type="RESPONSE"><con:mediaType xsi:nil="true"/><con:status>200</con:status><con:params/><con:element>data</con:element></con:representation><con:representation type="RESPONSE"><con:mediaType xsi:nil="true"/><con:status>0</con:status><con:params/><con:element>data</con:element></con:representation><con:representation type="RESPONSE"><con:mediaType xsi:nil="true"/><con:status>0</con:status><con:params/><con:element>data</con:element></con:representation><con:representation type="RESPONSE"><con:mediaType xsi:nil="true"/><con:status>0</con:status><con:params/><con:element>data</con:element></con:representation><con:representation type="RESPONSE"><con:mediaType xsi:nil="true"/><con:status>200</con:status><con:params/><con:element>data</con:element></con:representation><con:representation type="RESPONSE"><con:mediaType xsi:nil="true"/><con:status>200</con:status><con:params/><con:element>data</con:element></con:representation><con:representation type="RESPONSE"><con:mediaType xsi:nil="true"/><con:status>0</con:status><con:params/><con:element>data</con:element></con:representation><con:representation type="RESPONSE"><con:mediaType xsi:nil="true"/><con:status>0</con:status><con:params/><con:element>data</con:element></con:representation><con:representation type="RESPONSE"><con:mediaType xsi:nil="true"/><con:status>0</con:status><con:params/><con:element>data</con:element></con:representation><con:representation type="RESPONSE"><con:mediaType xsi:nil="true"/><con:status>0</con:status><con:params/><con:element>data</con:element></con:representation><con:representation type="RESPONSE"><con:mediaType xsi:nil="true"/><con:status>200</con:status><con:params/><con:element>data</con:element></con:representation><con:request name="Request 1" id="365ad868-d192-4738-aa8a-0a8403c3915f" mediaType="application/json" postQueryString="false"><con:settings><con:setting id="com.eviware.soapui.impl.wsdl.WsdlRequest@request-headers">&lt;xml-fragment/></con:setting></con:settings><con:endpoint>http://localhost:6070</con:endpoint><con:request>{
"id" : 5
}</con:request><con:originalUri>http://localhost/multipleCustomer/v1/manu</con:originalUri><con:credentials><con:authType>No Authorization</con:authType></con:credentials><con:jmsConfig JMSDeliveryMode="PERSISTENT"/><con:jmsPropertyConfig/><con:parameters/></con:request></con:method></con:resource><con:resource name="v15" path="/multipleCustomer/v1/CustOffer" id="958f88a6-e34b-4887-adbd-f3c40da39eef"><con:settings/><con:parameters/><con:method name="getCustomerOffer" id="d3d3c6b8-d801-4a53-a9fb-dda07033dd50" method="POST"><con:settings/><con:parameters/><con:representation type="RESPONSE"><con:mediaType>application/json;charset=UTF-8</con:mediaType><con:status>200</con:status><con:params/></con:representation><con:representation type="REQUEST"><con:mediaType>application/json</con:mediaType><con:params/></con:representation><con:representation type="FAULT"><con:mediaType>application/json;charset=UTF-8</con:mediaType><con:status>500 400</con:status><con:params/><con:element xmlns:manu="http://localhost/multipleCustomer/v1/manu">manu:Fault</con:element></con:representation><con:representation type="RESPONSE"><con:mediaType xsi:nil="true"/><con:status>0</con:status><con:params/><con:element>data</con:element></con:representation><con:representation type="RESPONSE"><con:mediaType xsi:nil="true"/><con:status>0</con:status><con:params/><con:element>data</con:element></con:representation><con:representation type="RESPONSE"><con:mediaType xsi:nil="true"/><con:status>200</con:status><con:params/><con:element>data</con:element></con:representation><con:representation type="RESPONSE"><con:mediaType xsi:nil="true"/><con:status>200</con:status><con:params/><con:element>data</con:element></con:representation><con:representation type="RESPONSE"><con:mediaType xsi:nil="true"/><con:status>0</con:status><con:params/><con:element>data</con:element></con:representation><con:representation type="RESPONSE"><con:mediaType xsi:nil="true"/><con:status>0</con:status><con:params/><con:element>data</con:element></con:representation><con:representation type="RESPONSE"><con:mediaType xsi:nil="true"/><con:status>0</con:status><con:params/><con:element>data</con:element></con:representation><con:representation type="RESPONSE"><con:mediaType xsi:nil="true"/><con:status>200</con:status><con:params/><con:element>data</con:element></con:representation><con:representation type="RESPONSE"><con:mediaType xsi:nil="true"/><con:status>200</con:status><con:params/><con:element>data</con:element></con:representation><con:representation type="RESPONSE"><con:mediaType xsi:nil="true"/><con:status>0</con:status><con:params/><con:element>data</con:element></con:representation><con:representation type="RESPONSE"><con:mediaType xsi:nil="true"/><con:status>0</con:status><con:params/><con:element>data</con:element></con:representation><con:representation type="RESPONSE"><con:mediaType xsi:nil="true"/><con:status>0</con:status><con:params/><con:element>data</con:element></con:representation><con:request name="Request 1" id="365ad868-d192-4738-aa8a-0a8403c3915f" mediaType="application/json" postQueryString="false"><con:settings><con:setting id="com.eviware.soapui.impl.wsdl.WsdlRequest@request-headers">&lt;xml-fragment/></con:setting></con:settings><con:endpoint>http://localhost:6070</con:endpoint><con:request>{
"offerNumber" : "23"
}</con:request><con:originalUri>http://localhost/multipleCustomer/v1/manu</con:originalUri><con:credentials><con:authType>No Authorization</con:authType></con:credentials><con:jmsConfig JMSDeliveryMode="PERSISTENT"/><con:jmsPropertyConfig/><con:parameters/></con:request></con:method></con:resource></con:interface><con:properties/><con:wssContainer/><con:oAuth2ProfileContainer/></con:soapui-project>